{"is_source_file": true, "format": "TypeScript (TSX)", "description": "This file defines the root layout component for a Next.js application, including metadata and the basic HTML structure wrapping child components.", "external_files": ["./globals.css"], "external_methods": [], "published": ["metadata", "RootLayout"], "classes": [], "methods": [{"name": "RootLayout", "description": "React functional component that provides the root layout for the Next.js app, rendering HTML structure with children content."}], "calls": ["React.createElement", "html", "body"], "search-terms": ["Next.js layout", "metadata", "RootLayout", "globals.css", "TSX", "suppressHydrationWarning"], "state": 2, "file_id": 5, "knowledge_revision": 22, "git_revision": "638af4847be62fabfcc5540b910de289508817b3", "ctags": [], "hash": "b8c9da91775e68b2caf15c64c76a1bf6", "format-version": 4, "code-base-name": "asset_management_frontend", "filename": "asset_management_frontend/src/app/layout.tsx", "revision_history": [{"22": "638af4847be62fabfcc5540b910de289508817b3"}]}